dadude/__init__.py
dadude/config.py
dadude/inspector.py
dadude/log.py
dadude/cli/convert.py
dadude/cli/duckdb_cli.py
dadude/cli/inspect.py
dadude/cli/read_table.py
dadude/cli/write_table.py
dadude/connector/dataset_viewer.py
dadude/connector/searchapi.py
dadude/connector/trino.py
dadude/connector/rag/client.py
dadude/connector/tidb/client.py
dadude/connector/tidb/source.py
dadude/orchestrator/assets.py
dadude/orchestrator/definitions.py
dadude/processor/delta_client.py
dadude/processor/duck_client.py
dadude/processor/ibis_client.py
dadude-0.3.5.dist-info/METADATA
dadude-0.3.5.dist-info/WHEEL
dadude-0.3.5.dist-info/licenses/LICENSE
dadude-0.3.5.dist-info/RECORD
