Metadata-Version: 2.4
Name: dadude
Version: 0.3.5
Summary: Lakehouse management, orchestration and data processing tool.
Author-email: Zhangda Xu <xuzhangda@patsnap.com>
License: MIT License
License-File: LICENSE
Requires-Python: >=3.10
Requires-Dist: boto3>=1.35.67
Requires-Dist: fire>=0.7.0
Requires-Dist: httpx>=0.27.2
Requires-Dist: ibis-framework[deltalake,duckdb,polars,visualization]>=9.5.0
Requires-Dist: loguru>=0.7.2
Requires-Dist: msgspec>=0.18.6
Requires-Dist: tenacity>=9.0.0
Requires-Dist: tqdm>=4.67.0
Provides-Extra: dag
Requires-Dist: dagster-deltalake-pandas>=0.25.3; extra == 'dag'
Requires-Dist: dagster-deltalake>=0.25.3; extra == 'dag'
Requires-Dist: dagster-webserver>=1.9.3; extra == 'dag'
